djng/__init__.py
djng/app_config.py
djng/app_settings.py
djng/middleware.py
djng/sekizai_processors.py
djng/urls.py
djng/core/__init__.py
djng/core/urlresolvers.py
djng/forms/__init__.py
djng/forms/angular_base.py
djng/forms/angular_model.py
djng/forms/angular_validation.py
djng/forms/fields.py
djng/forms/widgets.py
djng/static/djng/css/bootstrap3.css
djng/static/djng/css/fileupload.css
djng/static/djng/css/styles.css
djng/static/djng/icons/CREDITS.md
djng/static/djng/icons/_blank.png
djng/static/djng/icons/_page.png
djng/static/djng/icons/aac.png
djng/static/djng/icons/ai.png
djng/static/djng/icons/aiff.png
djng/static/djng/icons/avi.png
djng/static/djng/icons/bmp.png
djng/static/djng/icons/c.png
djng/static/djng/icons/cpp.png
djng/static/djng/icons/css.png
djng/static/djng/icons/csv.png
djng/static/djng/icons/dat.png
djng/static/djng/icons/dmg.png
djng/static/djng/icons/doc.png
djng/static/djng/icons/dotx.png
djng/static/djng/icons/dwg.png
djng/static/djng/icons/dxf.png
djng/static/djng/icons/eps.png
djng/static/djng/icons/exe.png
djng/static/djng/icons/flv.png
djng/static/djng/icons/gif.png
djng/static/djng/icons/h.png
djng/static/djng/icons/hpp.png
djng/static/djng/icons/html.png
djng/static/djng/icons/ics.png
djng/static/djng/icons/iso.png
djng/static/djng/icons/java.png
djng/static/djng/icons/jpg.png
djng/static/djng/icons/js.png
djng/static/djng/icons/key.png
djng/static/djng/icons/less.png
djng/static/djng/icons/mid.png
djng/static/djng/icons/mp3.png
djng/static/djng/icons/mp4.png
djng/static/djng/icons/mpg.png
djng/static/djng/icons/odf.png
djng/static/djng/icons/ods.png
djng/static/djng/icons/odt.png
djng/static/djng/icons/otp.png
djng/static/djng/icons/ots.png
djng/static/djng/icons/ott.png
djng/static/djng/icons/pdf.png
djng/static/djng/icons/php.png
djng/static/djng/icons/png.png
djng/static/djng/icons/ppt.png
djng/static/djng/icons/psd.png
djng/static/djng/icons/py.png
djng/static/djng/icons/qt.png
djng/static/djng/icons/rar.png
django_angular-2.3.1.dist-info/AUTHORS.md
django_angular-2.3.1.dist-info/LICENSE.txt
django_angular-2.3.1.dist-info/METADATA
django_angular-2.3.1.dist-info/WHEEL
django_angular-2.3.1.dist-info/top_level.txt
django_angular-2.3.1.dist-info/RECORD
