Metadata-Version: 2.1
Name: django-angular
Version: 2.3.1
Summary: Let Django play well with AngularJS
Home-page: https://github.com/jrief/django-angular
Author: Jacob Rief
Author-email: jacob.rief@gmail.com
License: MIT
Keywords: Django,AngularJS
Platform: OS Independent
Classifier: Environment :: Web Environment
Classifier: Framework :: Django
Classifier: Intended Audience :: Developers
Classifier: License :: OSI Approved :: MIT License
Classifier: Operating System :: OS Independent
Classifier: Programming Language :: Python
Classifier: Topic :: Software Development :: Libraries :: Python Modules
Classifier: Development Status :: 5 - Production/Stable
Classifier: Programming Language :: Python :: 3.5
Classifier: Programming Language :: Python :: 3.6
Classifier: Programming Language :: Python :: 3.7
Classifier: Programming Language :: Python :: 3.8
Classifier: Framework :: Django :: 2.1
Classifier: Framework :: Django :: 2.2
Classifier: Framework :: Django :: 3.0
Classifier: Framework :: Django :: 3.1
License-File: LICENSE.txt
License-File: AUTHORS.md
Requires-Dist: django>=2.1
